flamapy_mcp/__init__.py
flamapy_mcp/__main__.py
flamapy_mcp/server.py
flamapy_mcp-0.1.1.dist-info/licenses/LICENSE
flamapy_mcp-0.1.1.dist-info/METADATA
flamapy_mcp-0.1.1.dist-info/WHEEL
flamapy_mcp-0.1.1.dist-info/entry_points.txt
flamapy_mcp-0.1.1.dist-info/top_level.txt
flamapy_mcp-0.1.1.dist-info/RECORD
