Metadata-Version: 2.4
Name: flamapy-mcp
Version: 0.1.1
Summary: Flamapy MCP server to expose MCP tools to execute flamapy operations
Requires-Python: >=3.11
License-File: LICENSE
Requires-Dist: flamapy>=2.0.1
Requires-Dist: pydantic>=2.11.7
Requires-Dist: mcp>=1.0.0
Dynamic: license-file
